README.rst
setup.py
CUriTools.egg-info/PKG-INFO
CUriTools.egg-info/SOURCES.txt
CUriTools.egg-info/dependency_links.txt
CUriTools.egg-info/entry_points.txt
CUriTools.egg-info/requires.txt
CUriTools.egg-info/top_level.txt
curitools/__init__.py
curitools/curitools.py
curitools/settings.py
curitools/setup_problems.py
curitools/status.py
curitools/requestpages/__init__.py
curitools/requestpages/pages.py
curitools/templates/Makefile.c++
curitools/templates/base.cpp
curitools/templates/base.py
curitools/tests/__init__.py
curitools/tests/test_curitools.py
curitools/tests/test_settings.py
curitools/tests/test_setupproblems.py
curitools/tests/test_status.py
curitools/tests/test_subpage.py
curitools/views/__init__.py
curitools/views/academic.py
curitools/views/base_view.py