Metadata-Version: 1.1
Name: CUriTools
Version: 0.7.1
Summary: UNKNOWN
Home-page: https://github.com/gutorc92/curitools
Author: Gustavo Coelho
Author-email: gutorc@hotmail.com
License: Creative Commons Attribution-Noncommercial-Share Alike license
Keywords: uri
Platform: UNKNOWN
Classifier: Development Status :: 4 - Beta
Classifier: Intended Audience :: Developers
Classifier: Topic :: Software Development :: Build Tools
Classifier: Programming Language :: Python :: 3
Classifier: Programming Language :: Python :: 3.3
Classifier: Programming Language :: Python :: 3.4
Classifier: Programming Language :: Python :: 3.5
